pote/__init__.py
pote/_modidx.py
pote/all.py
pote/basic.py
pote/callback.py
pote/common.py
pote/config.py
pote/display.py
pote/logger_loguru.py
pote/project.py
pote/test.py
pote/widget.py
pote-0.1.1.dist-info/licenses/LICENSE
pote-0.1.1.dist-info/METADATA
pote-0.1.1.dist-info/WHEEL
pote-0.1.1.dist-info/entry_points.txt
pote-0.1.1.dist-info/top_level.txt
pote-0.1.1.dist-info/RECORD
