Metadata-Version: 2.4
Name: pote
Version: 0.1.1
Summary: Python helpers, utils or code not worthy ot its own repo
Home-page: https://github.com/civvic/pote
Author: Spikey
Author-email: civvic@gmail.com
License: Apache Software License 2.0
Keywords: python nbdev jupyter notebook javascript
Classifier: Development Status :: 4 - Beta
Classifier: Intended Audience :: Developers
Classifier: Natural Language :: English
Classifier: Programming Language :: Python :: 3.11
Classifier: Programming Language :: Python :: 3.12
Classifier: License :: OSI Approved :: Apache Software License
Requires-Python: >=3.11
License-File: LICENSE
Requires-Dist: fastcore>=1.5.28
Requires-Dist: rich>=13.3.2
Requires-Dist: ipywidgets>=8.1.5
Requires-Dist: jupyter_ui_poll>=1.0.0
Requires-Dist: loguru>=0.7.0
Provides-Extra: dev
Requires-Dist: notebook; extra == "dev"
Requires-Dist: jupyterlab; extra == "dev"
Requires-Dist: nbclassic; extra == "dev"
Requires-Dist: nbdev; extra == "dev"
Dynamic: author
Dynamic: author-email
Dynamic: classifier
Dynamic: description
Dynamic: description-content-type
Dynamic: home-page
Dynamic: keywords
Dynamic: license
Dynamic: license-file
Dynamic: provides-extra
Dynamic: requires-dist
Dynamic: requires-python
Dynamic: summary
